[
    {
        "_links": {
            "self": {
                "href": "https://soskweb.oktapreview.com/api/v1/users/00uo52jan5sMMmnVR0h7"
            }
        },
        "activated": null,
        "created": "2019-10-29T13:22:51.000Z",
        "credentials": {
            "emails": [
                {
                    "status": "VERIFIED",
                    "type": "PRIMARY",
                    "value": "groth@mailinator.com"
                }
            ],
            "provider": {
                "name": "OKTA",
                "type": "OKTA"
            }
        },
        "id": "00uo52jan5sMMmnVR0h7",
        "lastLogin": null,
        "lastUpdated": "2019-10-29T13:22:51.000Z",
        "passwordChanged": null,
        "profile": {
            "email": "groth@mailinator.com",
            "firstName": "Glen",
            "lastName": "Roth",
            "login": "groth@mailinator.com",
            "mobilePhone": null,
            "secondEmail": null
        },
        "status": "STAGED",
        "statusChanged": null,
        "type": {
            "id": "otynhf4ierORWVjme0h7"
        }
    },
    {
        "_links": {
            "self": {
                "href": "https://soskweb.oktapreview.com/api/v1/users/00urdfwygnrjK5wKI0h7"
            }
        },
        "activated": null,
        "created": "2020-05-05T19:30:42.000Z",
        "credentials": {
            "emails": [
                {
                    "status": "VERIFIED",
                    "type": "PRIMARY",
                    "value": "kamino142@example.com"
                }
            ],
            "password": {},
            "provider": {
                "name": "OKTA",
                "type": "OKTA"
            }
        },
        "id": "00urdfwygnrjK5wKI0h7",
        "lastLogin": null,
        "lastUpdated": "2020-05-05T19:30:43.000Z",
        "passwordChanged": "2020-05-05T19:30:43.000Z",
        "profile": {
            "displayName": "Kamino142 Yavin621",
            "email": "kamino142@example.com",
            "employeeNumber": "9141",
            "firstName": "Kamino142",
            "lastName": "Yavin621",
            "login": "kamino142@example.com",
            "managerId": "00urdg1z7mqiQotUo0h7",
            "mobilePhone": null,
            "secondEmail": null
        },
        "status": "STAGED",
        "statusChanged": null,
        "type": {
            "id": "otynhf4ierORWVjme0h7"
        }
    },
    {
        "_links": {
            "self": {
                "href": "https://soskweb.oktapreview.com/api/v1/users/00urdg0iukPSwBV1q0h7"
            }
        },
        "activated": null,
        "created": "2020-05-05T19:29:28.000Z",
        "credentials": {
            "emails": [
                {
                    "status": "VERIFIED",
                    "type": "PRIMARY",
                    "value": "obi-wan877@example.com"
                }
            ],
            "password": {},
            "provider": {
                "name": "OKTA",
                "type": "OKTA"
            }
        },
        "id": "00urdg0iukPSwBV1q0h7",
        "lastLogin": null,
        "lastUpdated": "2020-05-05T19:29:29.000Z",
        "passwordChanged": "2020-05-05T19:29:29.000Z",
        "profile": {
            "displayName": "Obi-Wan877 Obi-Wan105",
            "email": "obi-wan877@example.com",
            "employeeNumber": "2955",
            "firstName": "Obi-Wan877",
            "lastName": "Obi-Wan105",
            "login": "obi-wan877@example.com",
            "mobilePhone": null,
            "secondEmail": null,
            "title": "manager"
        },
        "status": "STAGED",
        "statusChanged": null,
        "type": {
            "id": "otynhf4ierORWVjme0h7"
        }
    },
    {
        "_links": {
            "self": {
                "href": "https://soskweb.oktapreview.com/api/v1/users/00urdg0ozbJjTpcrc0h7"
            }
        },
        "activated": null,
        "created": "2020-05-05T19:31:03.000Z",
        "credentials": {
            "emails": [
                {
                    "status": "VERIFIED",
                    "type": "PRIMARY",
                    "value": "lars724@example.com"
                }
            ],
            "password": {},
            "provider": {
                "name": "OKTA",
                "type": "OKTA"
            }
        },
        "id": "00urdg0ozbJjTpcrc0h7",
        "lastLogin": null,
        "lastUpdated": "2020-05-05T19:31:04.000Z",
        "passwordChanged": "2020-05-05T19:31:04.000Z",
        "profile": {
            "displayName": "lars724 lars967",
            "email": "lars724@example.com",
            "employeeNumber": "4204",
            "firstName": "lars724",
            "lastName": "lars967",
            "login": "lars724@example.com",
            "managerId": "00urdg0iukPSwBV1q0h7",
            "mobilePhone": null,
            "secondEmail": null
        },
        "status": "STAGED",
        "statusChanged": null,
        "type": {
            "id": "otynhf4ierORWVjme0h7"
        }
    },
    {
        "_links": {
            "self": {
                "href": "https://soskweb.oktapreview.com/api/v1/users/00urdg16g52CJ4X7Z0h7"
            }
        },
        "activated": null,
        "created": "2020-05-05T19:30:49.000Z",
        "credentials": {
            "emails": [
                {
                    "status": "VERIFIED",
                    "type": "PRIMARY",
                    "value": "beru634@example.com"
                }
            ],
            "password": {},
            "provider": {
                "name": "OKTA",
                "type": "OKTA"
            }
        },
        "id": "00urdg16g52CJ4X7Z0h7",
        "lastLogin": null,
        "lastUpdated": "2020-05-05T19:30:50.000Z",
        "passwordChanged": "2020-05-05T19:30:50.000Z",
        "profile": {
            "displayName": "Beru634 Hoth510",
            "email": "beru634@example.com",
            "employeeNumber": "8829",
            "firstName": "Beru634",
            "lastName": "Hoth510",
            "login": "beru634@example.com",
            "managerId": "00urdg30bwU5cAb4d0h7",
            "mobilePhone": null,
            "secondEmail": null
        },
        "status": "STAGED",
        "statusChanged": null,
        "type": {
            "id": "otynhf4ierORWVjme0h7"
        }
    },
    {
        "_links": {
            "self": {
                "href": "https://soskweb.oktapreview.com/api/v1/users/00urdg18mjaO9sloE0h7"
            }
        },
        "activated": null,
        "created": "2020-05-05T19:30:59.000Z",
        "credentials": {
            "emails": [
                {
                    "status": "VERIFIED",
                    "type": "PRIMARY",
                    "value": "kenobi863@example.com"
                }
            ],
            "password": {},
            "provider": {
                "name": "OKTA",
                "type": "OKTA"
            }
        },
        "id": "00urdg18mjaO9sloE0h7",
        "lastLogin": null,
        "lastUpdated": "2020-05-05T19:31:00.000Z",
        "passwordChanged": "2020-05-05T19:31:00.000Z",
        "profile": {
            "displayName": "Kenobi863 Endor592",
            "email": "kenobi863@example.com",
            "employeeNumber": "2477",
            "firstName": "Kenobi863",
            "lastName": "Endor592",
            "login": "kenobi863@example.com",
            "managerId": "00urdg1z7mqiQotUo0h7",
            "mobilePhone": null,
            "secondEmail": null
        },
        "status": "STAGED",
        "statusChanged": null,
        "type": {
            "id": "otynhf4ierORWVjme0h7"
        }
    },
    {
        "_links": {
            "self": {
                "href": "https://soskweb.oktapreview.com/api/v1/users/00urdg1jnjVMHevR80h7"
            }
        },
        "activated": null,
        "created": "2020-05-05T19:31:07.000Z",
        "credentials": {
            "emails": [
                {
                    "status": "VERIFIED",
                    "type": "PRIMARY",
                    "value": "obi-wan951@example.com"
                }
            ],
            "password": {},
            "provider": {
                "name": "OKTA",
                "type": "OKTA"
            }
        },
        "id": "00urdg1jnjVMHevR80h7",
        "lastLogin": null,
        "lastUpdated": "2020-05-05T19:31:08.000Z",
        "passwordChanged": "2020-05-05T19:31:08.000Z",
        "profile": {
            "displayName": "Obi-Wan951 Skywalker683",
            "email": "obi-wan951@example.com",
            "employeeNumber": "468",
            "firstName": "Obi-Wan951",
            "lastName": "Skywalker683",
            "login": "obi-wan951@example.com",
            "managerId": "00urdg30bwU5cAb4d0h7",
            "mobilePhone": null,
            "secondEmail": null
        },
        "status": "STAGED",
        "statusChanged": null,
        "type": {
            "id": "otynhf4ierORWVjme0h7"
        }
    },
    {
        "_links": {
            "self": {
                "href": "https://soskweb.oktapreview.com/api/v1/users/00urdg1z7mqiQotUo0h7"
            }
        },
        "activated": null,
        "created": "2020-05-05T19:29:32.000Z",
        "credentials": {
            "emails": [
                {
                    "status": "VERIFIED",
                    "type": "PRIMARY",
                    "value": "tatooine185@example.com"
                }
            ],
            "password": {},
            "provider": {
                "name": "OKTA",
                "type": "OKTA"
            }
        },
        "id": "00urdg1z7mqiQotUo0h7",
        "lastLogin": null,
        "lastUpdated": "2020-05-05T19:29:33.000Z",
        "passwordChanged": "2020-05-05T19:29:33.000Z",
        "profile": {
            "displayName": "Tatooine185 Tatooine998",
            "email": "tatooine185@example.com",
            "employeeNumber": "2952",
            "firstName": "Tatooine185",
            "lastName": "Tatooine998",
            "login": "tatooine185@example.com",
            "mobilePhone": null,
            "secondEmail": null,
            "title": "manager"
        },
        "status": "STAGED",
        "statusChanged": null,
        "type": {
            "id": "otynhf4ierORWVjme0h7"
        }
    },
    {
        "_links": {
            "self": {
                "href": "https://soskweb.oktapreview.com/api/v1/users/00urdg2ittO9mlDhK0h7"
            }
        },
        "activated": null,
        "created": "2020-05-05T19:31:13.000Z",
        "credentials": {
            "emails": [
                {
                    "status": "VERIFIED",
                    "type": "PRIMARY",
                    "value": "naboo927@example.com"
                }
            ],
            "password": {},
            "provider": {
                "name": "OKTA",
                "type": "OKTA"
            }
        },
        "id": "00urdg2ittO9mlDhK0h7",
        "lastLogin": null,
        "lastUpdated": "2020-05-05T19:31:14.000Z",
        "passwordChanged": "2020-05-05T19:31:14.000Z",
        "profile": {
            "displayName": "Naboo927 Whitesun240",
            "email": "naboo927@example.com",
            "employeeNumber": "1838",
            "firstName": "Naboo927",
            "lastName": "Whitesun240",
            "login": "naboo927@example.com",
            "managerId": "00urdg1z7mqiQotUo0h7",
            "mobilePhone": null,
            "secondEmail": null
        },
        "status": "STAGED",
        "statusChanged": null,
        "type": {
            "id": "otynhf4ierORWVjme0h7"
        }
    },
    {
        "_links": {
            "self": {
                "href": "https://soskweb.oktapreview.com/api/v1/users/00urdg2k4uFnQI0Qv0h7"
            }
        },
        "activated": null,
        "created": "2020-05-05T19:30:45.000Z",
        "credentials": {
            "emails": [
                {
                    "status": "VERIFIED",
                    "type": "PRIMARY",
                    "value": "vader554@example.com"
                }
            ],
            "password": {},
            "provider": {
                "name": "OKTA",
                "type": "OKTA"
            }
        },
        "id": "00urdg2k4uFnQI0Qv0h7",
        "lastLogin": null,
        "lastUpdated": "2020-05-05T19:30:46.000Z",
        "passwordChanged": "2020-05-05T19:30:46.000Z",
        "profile": {
            "displayName": "Vader554 Kenobi10",
            "email": "vader554@example.com",
            "employeeNumber": "8709",
            "firstName": "Vader554",
            "lastName": "Kenobi10",
            "login": "vader554@example.com",
            "managerId": "00urdg54zhBh0BmxZ0h7",
            "mobilePhone": null,
            "secondEmail": null
        },
        "status": "STAGED",
        "statusChanged": null,
        "type": {
            "id": "otynhf4ierORWVjme0h7"
        }
    },
    {
        "_links": {
            "self": {
                "href": "https://soskweb.oktapreview.com/api/v1/users/00urdg2wfdbta6JNJ0h7"
            }
        },
        "activated": null,
        "created": "2020-05-05T19:29:17.000Z",
        "credentials": {
            "emails": [
                {
                    "status": "VERIFIED",
                    "type": "PRIMARY",
                    "value": "endor892@example.com"
                }
            ],
            "password": {},
            "provider": {
                "name": "OKTA",
                "type": "OKTA"
            }
        },
        "id": "00urdg2wfdbta6JNJ0h7",
        "lastLogin": null,
        "lastUpdated": "2020-05-05T19:29:18.000Z",
        "passwordChanged": "2020-05-05T19:29:18.000Z",
        "profile": {
            "displayName": "Endor892 Kamino519",
            "email": "endor892@example.com",
            "employeeNumber": "6826",
            "firstName": "Endor892",
            "lastName": "Kamino519",
            "login": "endor892@example.com",
            "mobilePhone": null,
            "secondEmail": null,
            "title": "manager"
        },
        "status": "STAGED",
        "statusChanged": null,
        "type": {
            "id": "otynhf4ierORWVjme0h7"
        }
    },
    {
        "_links": {
            "self": {
                "href": "https://soskweb.oktapreview.com/api/v1/users/00urdg30bwU5cAb4d0h7"
            }
        },
        "activated": null,
        "created": "2020-05-05T19:29:22.000Z",
        "credentials": {
            "emails": [
                {
                    "status": "VERIFIED",
                    "type": "PRIMARY",
                    "value": "yavin38@example.com"
                }
            ],
            "password": {},
            "provider": {
                "name": "OKTA",
                "type": "OKTA"
            }
        },
        "id": "00urdg30bwU5cAb4d0h7",
        "lastLogin": null,
        "lastUpdated": "2020-05-05T19:29:23.000Z",
        "passwordChanged": "2020-05-05T19:29:23.000Z",
        "profile": {
            "displayName": "Yavin38 Alderaan617",
            "email": "yavin38@example.com",
            "employeeNumber": "366",
            "firstName": "Yavin38",
            "lastName": "Alderaan617",
            "login": "yavin38@example.com",
            "mobilePhone": null,
            "secondEmail": null,
            "title": "manager"
        },
        "status": "STAGED",
        "statusChanged": null,
        "type": {
            "id": "otynhf4ierORWVjme0h7"
        }
    },
    {
        "_links": {
            "self": {
                "href": "https://soskweb.oktapreview.com/api/v1/users/00urdg351kdcWgLbJ0h7"
            }
        },
        "activated": null,
        "created": "2020-05-05T19:30:56.000Z",
        "credentials": {
            "emails": [
                {
                    "status": "VERIFIED",
                    "type": "PRIMARY",
                    "value": "organa996@example.com"
                }
            ],
            "password": {},
            "provider": {
                "name": "OKTA",
                "type": "OKTA"
            }
        },
        "id": "00urdg351kdcWgLbJ0h7",
        "lastLogin": null,
        "lastUpdated": "2020-05-05T19:30:57.000Z",
        "passwordChanged": "2020-05-05T19:30:57.000Z",
        "profile": {
            "displayName": "Organa996 Coruscant995",
            "email": "organa996@example.com",
            "employeeNumber": "3367",
            "firstName": "Organa996",
            "lastName": "Coruscant995",
            "login": "organa996@example.com",
            "managerId": "00urdg30bwU5cAb4d0h7",
            "mobilePhone": null,
            "secondEmail": null
        },
        "status": "STAGED",
        "statusChanged": null,
        "type": {
            "id": "otynhf4ierORWVjme0h7"
        }
    },
    {
        "_links": {
            "self": {
                "href": "https://soskweb.oktapreview.com/api/v1/users/00urdg4ajo2kQ0wUe0h7"
            }
        },
        "activated": null,
        "created": "2020-05-05T19:30:53.000Z",
        "credentials": {
            "emails": [
                {
                    "status": "VERIFIED",
                    "type": "PRIMARY",
                    "value": "organa614@example.com"
                }
            ],
            "password": {},
            "provider": {
                "name": "OKTA",
                "type": "OKTA"
            }
        },
        "id": "00urdg4ajo2kQ0wUe0h7",
        "lastLogin": null,
        "lastUpdated": "2020-05-05T19:30:54.000Z",
        "passwordChanged": "2020-05-05T19:30:54.000Z",
        "profile": {
            "displayName": "Organa614 Coruscant147",
            "email": "organa614@example.com",
            "employeeNumber": "7933",
            "firstName": "Organa614",
            "lastName": "Coruscant147",
            "login": "organa614@example.com",
            "managerId": "00urdg2wfdbta6JNJ0h7",
            "mobilePhone": null,
            "secondEmail": null
        },
        "status": "STAGED",
        "statusChanged": null,
        "type": {
            "id": "otynhf4ierORWVjme0h7"
        }
    },
    {
        "_links": {
            "self": {
                "href": "https://soskweb.oktapreview.com/api/v1/users/00urdg4c4iq6Pfg570h7"
            }
        },
        "activated": null,
        "created": "2020-05-05T19:31:10.000Z",
        "credentials": {
            "emails": [
                {
                    "status": "VERIFIED",
                    "type": "PRIMARY",
                    "value": "naboo908@example.com"
                }
            ],
            "password": {},
            "provider": {
                "name": "OKTA",
                "type": "OKTA"
            }
        },
        "id": "00urdg4c4iq6Pfg570h7",
        "lastLogin": null,
        "lastUpdated": "2020-05-05T19:31:11.000Z",
        "passwordChanged": "2020-05-05T19:31:11.000Z",
        "profile": {
            "displayName": "Naboo908 Dagobah720",
            "email": "naboo908@example.com",
            "employeeNumber": "998",
            "firstName": "Naboo908",
            "lastName": "Dagobah720",
            "login": "naboo908@example.com",
            "managerId": "00urdg30bwU5cAb4d0h7",
            "mobilePhone": null,
            "secondEmail": null
        },
        "status": "STAGED",
        "statusChanged": null,
        "type": {
            "id": "otynhf4ierORWVjme0h7"
        }
    },
    {
        "_links": {
            "self": {
                "href": "https://soskweb.oktapreview.com/api/v1/users/00urdg54zhBh0BmxZ0h7"
            }
        },
        "activated": null,
        "created": "2020-05-05T19:29:25.000Z",
        "credentials": {
            "emails": [
                {
                    "status": "VERIFIED",
                    "type": "PRIMARY",
                    "value": "beru665@example.com"
                }
            ],
            "password": {},
            "provider": {
                "name": "OKTA",
                "type": "OKTA"
            }
        },
        "id": "00urdg54zhBh0BmxZ0h7",
        "lastLogin": null,
        "lastUpdated": "2020-05-05T19:29:26.000Z",
        "passwordChanged": "2020-05-05T19:29:26.000Z",
        "profile": {
            "displayName": "Beru665 Kenobi623",
            "email": "beru665@example.com",
            "employeeNumber": "7218",
            "firstName": "Beru665",
            "lastName": "Kenobi623",
            "login": "beru665@example.com",
            "mobilePhone": null,
            "secondEmail": null,
            "title": "manager"
        },
        "status": "STAGED",
        "statusChanged": null,
        "type": {
            "id": "otynhf4ierORWVjme0h7"
        }
    },
    {
        "_links": {
            "self": {
                "href": "https://soskweb.oktapreview.com/api/v1/users/00unhf4ifeZjwmvXV0h7"
            }
        },
        "activated": null,
        "created": "2019-09-17T19:13:09.000Z",
        "credentials": {
            "emails": [
                {
                    "status": "VERIFIED",
                    "type": "PRIMARY",
                    "value": "indranil.jha@okta.com"
                }
            ],
            "password": {},
            "provider": {
                "name": "OKTA",
                "type": "OKTA"
            },
            "recovery_question": {
                "question": "What is the food you least liked as a child?"
            }
        },
        "id": "00unhf4ifeZjwmvXV0h7",
        "lastLogin": "2020-07-01T15:08:05.000Z",
        "lastUpdated": "2020-06-24T20:45:32.000Z",
        "passwordChanged": "2019-10-15T16:02:47.000Z",
        "profile": {
            "accountNumber": "ABCD",
            "email": "indranil.jha@okta.com",
            "firstName": "Indranil",
            "hasOptedOutGeoTracking": "no",
            "hasOptedOutProcessing": "no",
            "hasOptedOutProfiling": "no",
            "hasOptedOutSolicit": "no",
            "hasOptedOutTracking": "no",
            "lastName": "Jha",
            "login": "indranil.jha@okta.com",
            "mobilePhone": null,
            "secondEmail": null
        },
        "status": "ACTIVE",
        "statusChanged": "2019-09-17T19:27:24.000Z",
        "type": {
            "id": "otynhf4ierORWVjme0h7"
        }
    },
    {
        "_links": {
            "self": {
                "href": "https://soskweb.oktapreview.com/api/v1/users/00unvek0bwsqFovOe0h7"
            }
        },
        "activated": "2019-10-14T23:05:47.000Z",
        "created": "2019-10-14T23:05:47.000Z",
        "credentials": {
            "emails": [
                {
                    "status": "VERIFIED",
                    "type": "PRIMARY",
                    "value": "zee.khoo@okta.com"
                }
            ],
            "password": {},
            "provider": {
                "name": "OKTA",
                "type": "OKTA"
            },
            "recovery_question": {
                "question": "What is the food you least liked as a child?"
            }
        },
        "id": "00unvek0bwsqFovOe0h7",
        "lastLogin": "2019-10-28T18:14:32.000Z",
        "lastUpdated": "2019-10-14T23:06:12.000Z",
        "passwordChanged": "2019-10-14T23:06:12.000Z",
        "profile": {
            "email": "zee.khoo@okta.com",
            "firstName": "Zee",
            "lastName": "Khoo",
            "login": "zee.khoo@okta.com",
            "mobilePhone": null,
            "secondEmail": null
        },
        "status": "ACTIVE",
        "statusChanged": "2019-10-14T23:06:12.000Z",
        "type": {
            "id": "otynhf4ierORWVjme0h7"
        }
    },
    {
        "_links": {
            "self": {
                "href": "https://soskweb.oktapreview.com/api/v1/users/00unxjl7ayLYxSUgt0h7"
            }
        },
        "activated": "2019-10-17T22:03:43.000Z",
        "created": "2019-10-17T22:03:43.000Z",
        "credentials": {
            "emails": [
                {
                    "status": "VERIFIED",
                    "type": "PRIMARY",
                    "value": "mike.tran@okta.com"
                }
            ],
            "password": {},
            "provider": {
                "name": "OKTA",
                "type": "OKTA"
            },
            "recovery_question": {
                "question": "What is the food you least liked as a child?"
            }
        },
        "id": "00unxjl7ayLYxSUgt0h7",
        "lastLogin": "2019-10-17T22:09:33.000Z",
        "lastUpdated": "2019-10-17T22:09:33.000Z",
        "passwordChanged": "2019-10-17T22:09:33.000Z",
        "profile": {
            "email": "mike.tran@okta.com",
            "firstName": "Mike",
            "lastName": "Tran",
            "login": "mike.tran@okta.com",
            "mobilePhone": null,
            "secondEmail": null
        },
        "status": "ACTIVE",
        "statusChanged": "2019-10-17T22:09:33.000Z",
        "type": {
            "id": "otynhf4ierORWVjme0h7"
        }
    },
    {
        "_links": {
            "self": {
                "href": "https://soskweb.oktapreview.com/api/v1/users/00uo56ab29qmo98TC0h7"
            }
        },
        "activated": "2019-10-29T16:16:39.000Z",
        "created": "2019-10-29T16:16:39.000Z",
        "credentials": {
            "emails": [
                {
                    "status": "VERIFIED",
                    "type": "PRIMARY",
                    "value": "jswift@mailinator.com"
                }
            ],
            "password": {},
            "provider": {
                "name": "OKTA",
                "type": "OKTA"
            },
            "recovery_question": {
                "question": "What is the food you least liked as a child?"
            }
        },
        "id": "00uo56ab29qmo98TC0h7",
        "lastLogin": "2019-10-29T16:19:21.000Z",
        "lastUpdated": "2019-10-29T16:18:57.000Z",
        "passwordChanged": "2019-10-29T16:18:56.000Z",
        "profile": {
            "email": "jswift@mailinator.com",
            "firstName": "Jonathon",
            "lastName": "Swift",
            "login": "jswift@mailinator.com",
            "mobilePhone": null,
            "secondEmail": null
        },
        "status": "ACTIVE",
        "statusChanged": "2019-10-29T16:18:56.000Z",
        "type": {
            "id": "otynhf4ierORWVjme0h7"
        }
    },
    {
        "_links": {
            "self": {
                "href": "https://soskweb.oktapreview.com/api/v1/users/00updav9crWZJbMIL0h7"
            }
        },
        "activated": "2020-01-21T17:20:04.000Z",
        "created": "2020-01-21T17:20:02.000Z",
        "credentials": {
            "emails": [
                {
                    "status": "VERIFIED",
                    "type": "PRIMARY",
                    "value": "mobileadmin@demo.com"
                },
                {
                    "status": "VERIFIED",
                    "type": "SECONDARY",
                    "value": "indranil.jha@okta.com"
                }
            ],
            "password": {},
            "provider": {
                "name": "OKTA",
                "type": "OKTA"
            },
            "recovery_question": {
                "question": "What is the food you least liked as a child?"
            }
        },
        "id": "00updav9crWZJbMIL0h7",
        "lastLogin": "2020-01-21T17:51:28.000Z",
        "lastUpdated": "2020-01-21T17:20:48.000Z",
        "passwordChanged": "2020-01-21T17:20:03.000Z",
        "profile": {
            "email": "mobileadmin@demo.com",
            "firstName": "Mobile",
            "lastName": "Admin",
            "login": "mobileadmin@demo.com",
            "mobilePhone": null,
            "secondEmail": "indranil.jha@okta.com"
        },
        "status": "ACTIVE",
        "statusChanged": "2020-01-21T17:20:04.000Z",
        "type": {
            "id": "otynhf4ierORWVjme0h7"
        }
    },
    {
        "_links": {
            "self": {
                "href": "https://soskweb.oktapreview.com/api/v1/users/00upuz39htginx6fY0h7"
            }
        },
        "activated": "2020-02-20T17:08:14.000Z",
        "created": "2020-02-20T17:08:13.000Z",
        "credentials": {
            "emails": [
                {
                    "status": "UNVERIFIED",
                    "type": "PRIMARY",
                    "value": "jmiller@mailinator.com"
                }
            ],
            "password": {},
            "provider": {
                "name": "OKTA",
                "type": "OKTA"
            },
            "recovery_question": {
                "question": "What is the food you least liked as a child?"
            }
        },
        "id": "00upuz39htginx6fY0h7",
        "lastLogin": "2020-02-20T17:08:15.000Z",
        "lastUpdated": "2020-02-20T17:08:28.000Z",
        "passwordChanged": "2020-02-20T17:08:14.000Z",
        "profile": {
            "email": "jmiller@mailinator.com",
            "firstName": "John",
            "hasOptedOutGeoTracking": "yes",
            "hasOptedOutProcessing": "no",
            "hasOptedOutProfiling": "yes",
            "hasOptedOutSolicit": "no",
            "hasOptedOutTracking": "yes",
            "lastName": "Miller",
            "login": "jmiller@mailinator.com",
            "mobilePhone": null,
            "privacyPreferencesUpdated": "2020-02-20T17:08:13+00:00",
            "salesforceRecordNumber": "0033k00003HCcqOAAT",
            "secondEmail": null
        },
        "status": "ACTIVE",
        "statusChanged": "2020-02-20T17:08:14.000Z",
        "type": {
            "id": "otynhf4ierORWVjme0h7"
        }
    },
    {
        "_links": {
            "self": {
                "href": "https://soskweb.oktapreview.com/api/v1/users/00upuzc4f2TvjplLJ0h7"
            }
        },
        "activated": "2020-02-20T17:23:12.000Z",
        "created": "2020-02-20T17:23:11.000Z",
        "credentials": {
            "emails": [
                {
                    "status": "UNVERIFIED",
                    "type": "PRIMARY",
                    "value": "sdowns@mailinator.com"
                }
            ],
            "password": {},
            "provider": {
                "name": "OKTA",
                "type": "OKTA"
            },
            "recovery_question": {
                "question": "What is the food you least liked as a child?"
            }
        },
        "id": "00upuzc4f2TvjplLJ0h7",
        "lastLogin": "2020-02-20T17:23:13.000Z",
        "lastUpdated": "2020-02-20T17:23:25.000Z",
        "passwordChanged": "2020-02-20T17:23:12.000Z",
        "profile": {
            "email": "sdowns@mailinator.com",
            "firstName": "Sally",
            "hasOptedOutGeoTracking": "yes",
            "hasOptedOutProcessing": "yes",
            "hasOptedOutProfiling": "no",
            "hasOptedOutSolicit": "no",
            "hasOptedOutTracking": "yes",
            "lastName": "Downs",
            "login": "sdowns@mailinator.com",
            "mobilePhone": null,
            "privacyPreferencesUpdated": "2020-02-20T17:23:11+00:00",
            "salesforceRecordNumber": "0033k00003HCd5JAAT",
            "secondEmail": null
        },
        "status": "ACTIVE",
        "statusChanged": "2020-02-20T17:23:12.000Z",
        "type": {
            "id": "otynhf4ierORWVjme0h7"
        }
    },
    {
        "_links": {
            "self": {
                "href": "https://soskweb.oktapreview.com/api/v1/users/00uqxvpcmso1d8kxR0h7"
            }
        },
        "activated": "2020-04-14T19:53:03.000Z",
        "created": "2020-04-14T19:53:02.000Z",
        "credentials": {
            "emails": [
                {
                    "status": "VERIFIED",
                    "type": "PRIMARY",
                    "value": "pmcdowell@okta.com"
                }
            ],
            "password": {},
            "provider": {
                "name": "OKTA",
                "type": "OKTA"
            },
            "recovery_question": {
                "question": "What is the food you least liked as a child?"
            }
        },
        "id": "00uqxvpcmso1d8kxR0h7",
        "lastLogin": "2020-04-14T20:59:43.000Z",
        "lastUpdated": "2020-04-14T20:59:43.000Z",
        "passwordChanged": "2020-04-14T20:59:42.000Z",
        "profile": {
            "email": "pmcdowell@okta.com",
            "firstName": "Patrick",
            "lastName": "McDowell",
            "login": "pmcdowell@okta.com",
            "mobilePhone": null,
            "secondEmail": null
        },
        "status": "ACTIVE",
        "statusChanged": "2020-04-14T20:59:42.000Z",
        "type": {
            "id": "otynhf4ierORWVjme0h7"
        }
    },
    {
        "_links": {
            "self": {
                "href": "https://soskweb.oktapreview.com/api/v1/users/00urg78ctxM67grwa0h7"
            }
        },
        "activated": "2020-05-08T21:14:39.000Z",
        "created": "2020-05-08T21:14:38.000Z",
        "credentials": {
            "emails": [
                {
                    "status": "VERIFIED",
                    "type": "PRIMARY",
                    "value": "maneesh.sahu@okta.com"
                }
            ],
            "password": {},
            "provider": {
                "name": "OKTA",
                "type": "OKTA"
            }
        },
        "id": "00urg78ctxM67grwa0h7",
        "lastLogin": null,
        "lastUpdated": "2020-05-08T21:14:46.000Z",
        "passwordChanged": "2020-05-08T21:14:46.000Z",
        "profile": {
            "email": "maneesh.sahu@okta.com",
            "firstName": "Maneesh",
            "lastName": "Sahu",
            "login": "maneesh.sahu@okta.com",
            "mobilePhone": null,
            "secondEmail": null
        },
        "status": "ACTIVE",
        "statusChanged": "2020-05-08T21:14:46.000Z",
        "type": {
            "id": "otynhf4ierORWVjme0h7"
        }
    },
    {
        "_links": {
            "self": {
                "href": "https://soskweb.oktapreview.com/api/v1/users/00urxoizd9Wy7xhJB0h7"
            }
        },
        "activated": "2020-06-03T21:35:23.000Z",
        "created": "2020-06-03T21:35:22.000Z",
        "credentials": {
            "emails": [
                {
                    "status": "VERIFIED",
                    "type": "PRIMARY",
                    "value": "wdawson@example.com"
                }
            ],
            "password": {},
            "provider": {
                "name": "OKTA",
                "type": "OKTA"
            },
            "recovery_question": {
                "question": "What is the food you least liked as a child?"
            }
        },
        "id": "00urxoizd9Wy7xhJB0h7",
        "lastLogin": "2020-06-26T16:30:35.000Z",
        "lastUpdated": "2020-06-26T16:31:44.000Z",
        "passwordChanged": "2020-06-04T17:49:38.000Z",
        "profile": {
            "email": "wdawson@example.com",
            "firstName": "Wils",
            "hasOptedOutGeoTracking": "no",
            "hasOptedOutProcessing": "no",
            "hasOptedOutProfiling": "no",
            "hasOptedOutSolicit": "no",
            "hasOptedOutTracking": "no",
            "lastName": "Dawson",
            "login": "wdawson@example.com",
            "mobilePhone": null,
            "secondEmail": null
        },
        "status": "ACTIVE",
        "statusChanged": "2020-06-04T17:49:38.000Z",
        "type": {
            "id": "otynhf4ierORWVjme0h7"
        }
    },
    {
        "_links": {
            "self": {
                "href": "https://soskweb.oktapreview.com/api/v1/users/00ury71ehx9O2mA0p0h7"
            }
        },
        "activated": "2020-06-04T15:09:05.000Z",
        "created": "2020-06-04T15:09:04.000Z",
        "credentials": {
            "emails": [
                {
                    "status": "VERIFIED",
                    "type": "PRIMARY",
                    "value": "jwells@mailinator.com"
                }
            ],
            "password": {},
            "provider": {
                "name": "OKTA",
                "type": "OKTA"
            },
            "recovery_question": {
                "question": "What is the food you least liked as a child?"
            }
        },
        "id": "00ury71ehx9O2mA0p0h7",
        "lastLogin": "2020-06-05T18:04:36.000Z",
        "lastUpdated": "2020-06-05T18:03:58.000Z",
        "passwordChanged": "2020-06-05T18:03:58.000Z",
        "profile": {
            "email": "jwells@mailinator.com",
            "firstName": "John",
            "lastName": "Wells",
            "login": "jwells@mailinator.com",
            "mobilePhone": null,
            "secondEmail": null
        },
        "status": "ACTIVE",
        "statusChanged": "2020-06-04T17:57:51.000Z",
        "type": {
            "id": "otynhf4ierORWVjme0h7"
        }
    },
    {
        "_links": {
            "self": {
                "href": "https://soskweb.oktapreview.com/api/v1/users/00us9rh9w5d9tk06P0h7"
            }
        },
        "activated": "2020-06-23T13:18:06.000Z",
        "created": "2020-06-23T13:18:05.000Z",
        "credentials": {
            "emails": [
                {
                    "status": "VERIFIED",
                    "type": "PRIMARY",
                    "value": "dcrane@mailinator.com"
                },
                {
                    "status": "VERIFIED",
                    "type": "SECONDARY",
                    "value": ""
                }
            ],
            "password": {},
            "provider": {
                "name": "OKTA",
                "type": "OKTA"
            }
        },
        "id": "00us9rh9w5d9tk06P0h7",
        "lastLogin": "2020-06-23T15:24:42.000Z",
        "lastUpdated": "2020-06-23T13:20:03.000Z",
        "passwordChanged": "2020-06-23T13:18:06.000Z",
        "profile": {
            "email": "dcrane@mailinator.com",
            "firstName": "Danny",
            "hasOptedOutGeoTracking": "no",
            "hasOptedOutProcessing": "no",
            "hasOptedOutProfiling": "no",
            "hasOptedOutSolicit": "no",
            "hasOptedOutTracking": "no",
            "lastName": "Crane",
            "login": "dcrane@mailinator.com",
            "mobilePhone": null,
            "privacyPreferencesUpdated": "2020-06-22T23:01:53+00:00",
            "salesforceRecordNumber": "0033k00003KennbAAB",
            "secondEmail": ""
        },
        "status": "ACTIVE",
        "statusChanged": "2020-06-23T13:18:06.000Z",
        "type": {
            "id": "otynhf4ierORWVjme0h7"
        }
    }
]